<?xml version="1.0" encoding="ISO-8859-1"?>

<ACTIONS>


	<ACTION name="ALIGN_EXPERT_ACTION" 
			class="it.eng.spagobi.qbe.queryinspector.service.AlignExpertAction" 
			scope="REQUEST">
			
		<CONFIG></CONFIG>
	</ACTION>
	
	
	<ACTION name="COMPOSE_RESUME_QUERY_ACTION" 
			class="it.eng.spagobi.qbe.queryinspector.service.ComposeResumeQueryAction" 
			scope="REQUEST">
			
		<CONFIG></CONFIG>
	</ACTION>
	
	
	 <ACTION name="UPDATE_EXPERT_ACTION" 
	 		class="it.eng.spagobi.qbe.queryinspector.service.UpdateExpertAction" 
	 		scope="REQUEST">
	 		
		<CONFIG></CONFIG>
	</ACTION>
	
	
	<ACTION name="UPDATE_FIELD_RESUME_ACTION" 
			class="it.eng.spagobi.qbe.queryinspector.service.UpdateFieldsForResumeAction" 
			scope="REQUEST">	
			
		<CONFIG></CONFIG>
	</ACTION> 
	
	
	<ACTION name="UPDATE_PREVIEW_MODE_ACTION" 
			class="it.eng.spagobi.qbe.queryinspector.service.UpdatePreviewModeAction"  
			scope="REQUEST">
			
		<CONFIG></CONFIG>
	</ACTION>
	
	
</ACTIONS>

